auxiliary/__init__.py
auxiliary/conversion.py
auxiliary/io.py
auxiliary/nifti/__init__.py
auxiliary/nifti/io.py
auxiliary/normalization/__init__.py
auxiliary/normalization/demo_normalizer.py
auxiliary/normalization/functional.py
auxiliary/normalization/normalizer_base.py
auxiliary/normalization/percentile_normalizer.py
auxiliary/normalization/windowing_normalizer.py
auxiliary/runscript.py
auxiliary/tiff/__init__.py
auxiliary/tiff/io.py
auxiliary/turbopath/__init__.py
auxiliary/turbopath/turbopath.py
auxiliary-0.4.1.dist-info/LICENSE
auxiliary-0.4.1.dist-info/METADATA
auxiliary-0.4.1.dist-info/WHEEL
auxiliary-0.4.1.dist-info/RECORD
