Metadata-Version: 2.3
Name: auxiliary
Version: 0.4.1
Summary: TODO.
License: AGPL-3.0
Author: Florian Kofler
Author-email: florian.kofler@tum.de
Requires-Python: >=3.10,<4.0
Classifier: License :: OSI Approved :: GNU Affero General Public License v3
Classifier: Programming Language :: Python :: 3
Classifier: Programming Language :: Python :: 3.10
Classifier: Programming Language :: Python :: 3.11
Classifier: Programming Language :: Python :: 3.12
Classifier: Programming Language :: Python :: 3.13
Provides-Extra: dcm2niix
Requires-Dist: dcm2niix (>=1.0.20250506) ; extra == "dcm2niix"
Requires-Dist: loguru (>=0.7.3,<0.8.0)
Requires-Dist: numpy (>=1.24)
Requires-Dist: path (>=17.0.0)
Requires-Dist: pillow (>=10.0.0)
Requires-Dist: simpleitk (>=2.2.1)
Requires-Dist: tifffile (>=2023.8.25)
Project-URL: Repository, https://github.com/BrainLesion/auxiliary
